auth_style/__init__.py
auth_style/apps.py
auth_style/static/auth_style/dist/styles.css
auth_style/static/auth_style/dist/styles.css.map
auth_style/templates/allauth/elements/alert.html
auth_style/templates/allauth/elements/badge.html
auth_style/templates/allauth/elements/button.html
auth_style/templates/allauth/elements/button_group.html
auth_style/templates/allauth/elements/details.html
auth_style/templates/allauth/elements/field.html
auth_style/templates/allauth/elements/fields.html
auth_style/templates/allauth/elements/form.html
auth_style/templates/allauth/elements/h1.html
auth_style/templates/allauth/elements/h2.html
auth_style/templates/allauth/elements/hr.html
auth_style/templates/allauth/elements/img.html
auth_style/templates/allauth/elements/p.html
auth_style/templates/allauth/elements/panel.html
auth_style/templates/allauth/elements/provider.html
auth_style/templates/allauth/elements/provider_list.html
auth_style/templates/allauth/elements/table.html
auth_style/templates/allauth/elements/tbody.html
auth_style/templates/allauth/elements/td.html
auth_style/templates/allauth/elements/th.html
auth_style/templates/allauth/elements/thead.html
auth_style/templates/allauth/elements/tr.html
auth_style/templates/allauth/layouts/base.html
auth_style/templates/auth_style/base.html
auth_style/templates/auth_style/extra_head.html
auth_style/templates/auth_style/site_name.html
django_auth_style-0.14.0.dist-info/METADATA
django_auth_style-0.14.0.dist-info/WHEEL
django_auth_style-0.14.0.dist-info/licenses/LICENSE
django_auth_style-0.14.0.dist-info/licenses/NOTICE
django_auth_style-0.14.0.dist-info/RECORD
