Metadata-Version: 2.4
Name: django-auth-style
Version: 0.14.0
Summary: Django template styling for django-allauth and django-oauth-toolkit.
Project-URL: Repository, https://github.com/kitware-resonant/django-auth-style
Project-URL: Bug Reports, https://github.com/kitware-resonant/django-auth-style/issues
Maintainer-email: "Kitware, Inc." <kitware@kitware.com>
License-Expression: Apache-2.0
License-File: LICENSE
License-File: NOTICE
Keywords: allauth,django,django-allauth,django-oauth-toolkit,kitware-resonant,resonant,style,styling
Classifier: Development Status :: 3 - Alpha
Classifier: Environment :: Web Environment
Classifier: Framework :: Django
Classifier: Framework :: Django :: 5
Classifier: Framework :: Django :: 5.2
Classifier: Framework :: Django :: 6
Classifier: Framework :: Django :: 6.0
Classifier: Intended Audience :: Developers
Classifier: Operating System :: OS Independent
Classifier: Programming Language :: Python
Classifier: Programming Language :: Python :: 3
Classifier: Programming Language :: Python :: 3.12
Classifier: Programming Language :: Python :: 3.13
Classifier: Programming Language :: Python :: 3.14
Requires-Python: >=3.12
Requires-Dist: django>=5.2
Provides-Extra: allauth
Requires-Dist: django-allauth>=0.63; extra == 'allauth'
Provides-Extra: oauth-toolkit
Requires-Dist: django-oauth-toolkit; extra == 'oauth-toolkit'
